html_extract/__init__.py
html_extract/batch.py
html_extract/cli.py
html_extract/config.py
html_extract/extract.py
html_extract/logging.py
html_extract/output.py
html_extract-0.7.0.dist-info/licenses/LICENSE
html_extract-0.7.0.dist-info/METADATA
html_extract-0.7.0.dist-info/WHEEL
html_extract-0.7.0.dist-info/entry_points.txt
html_extract-0.7.0.dist-info/top_level.txt
html_extract-0.7.0.dist-info/RECORD
