Metadata-Version: 2.4
Name: html-extract
Version: 0.7.0
Summary: Extract structured data from HTML files using declarative configuration files (YAML or JSON)
Author: michzad
License-Expression: MIT
Keywords: html,extraction,scraping,data,yaml,json,configuration
Classifier: Development Status :: 4 - Beta
Classifier: Intended Audience :: Developers
Classifier: Intended Audience :: Science/Research
Classifier: Programming Language :: Python :: 3
Classifier: Programming Language :: Python :: 3.9
Classifier: Programming Language :: Python :: 3.10
Classifier: Programming Language :: Python :: 3.11
Classifier: Programming Language :: Python :: 3.12
Classifier: Topic :: Software Development :: Libraries :: Python Modules
Classifier: Topic :: Text Processing :: Markup :: HTML
Classifier: Topic :: Utilities
Requires-Python: >=3.9
License-File: LICENSE
Requires-Dist: beautifulsoup4>=4.9.0
Requires-Dist: pandas>=2.0.0
Requires-Dist: pyyaml>=5.4.0
Requires-Dist: lxml>=4.6.0
Requires-Dist: tqdm>=4.64.0
Provides-Extra: dev
Requires-Dist: pytest>=7.0.0; extra == "dev"
Requires-Dist: build; extra == "dev"
Requires-Dist: twine; extra == "dev"
Dynamic: license-file
